aleksis/apps/untis/__init__.py
aleksis/apps/untis/apps.py
aleksis/apps/untis/commands.py
aleksis/apps/untis/data_checks.py
aleksis/apps/untis/locale/ar/LC_MESSAGES/django.mo
aleksis/apps/untis/locale/ar/LC_MESSAGES/django.po
aleksis/apps/untis/locale/de_DE/LC_MESSAGES/django.mo
aleksis/apps/untis/locale/de_DE/LC_MESSAGES/django.po
aleksis/apps/untis/locale/fr/LC_MESSAGES/django.mo
aleksis/apps/untis/locale/fr/LC_MESSAGES/django.po
aleksis/apps/untis/locale/la/LC_MESSAGES/django.mo
aleksis/apps/untis/locale/la/LC_MESSAGES/django.po
aleksis/apps/untis/locale/nb_NO/LC_MESSAGES/django.mo
aleksis/apps/untis/locale/nb_NO/LC_MESSAGES/django.po
aleksis/apps/untis/locale/ru/LC_MESSAGES/django.mo
aleksis/apps/untis/locale/ru/LC_MESSAGES/django.po
aleksis/apps/untis/locale/tr_TR/LC_MESSAGES/django.mo
aleksis/apps/untis/locale/tr_TR/LC_MESSAGES/django.po
aleksis/apps/untis/locale/uk/LC_MESSAGES/django.mo
aleksis/apps/untis/locale/uk/LC_MESSAGES/django.po
aleksis/apps/untis/management/commands/__init__.py
aleksis/apps/untis/management/commands/move_dates_for_testing.py
aleksis/apps/untis/management/commands/untis_import_mysql.py
aleksis/apps/untis/migrations/0001_initial.py
aleksis/apps/untis/migrations/0002_auto_20200820_1542.py
aleksis/apps/untis/migrations/0003_guess_school_id.py
aleksis/apps/untis/migrations/__init__.py
aleksis/apps/untis/model_extensions.py
aleksis/apps/untis/models.py
aleksis/apps/untis/preferences.py
aleksis/apps/untis/rules.py
aleksis/apps/untis/settings.py
aleksis/apps/untis/tasks.py
aleksis/apps/untis/tests/util/test_mysql_util.py
aleksis/apps/untis/util/mysql/importers/absences.py
aleksis/apps/untis/util/mysql/importers/common_data.py
aleksis/apps/untis/util/mysql/importers/events.py
aleksis/apps/untis/util/mysql/importers/exams.py
aleksis/apps/untis/util/mysql/importers/holidays.py
aleksis/apps/untis/util/mysql/importers/lessons.py
aleksis/apps/untis/util/mysql/importers/substitutions.py
aleksis/apps/untis/util/mysql/importers/terms.py
aleksis_app_untis-3.0.dist-info/METADATA
aleksis_app_untis-3.0.dist-info/WHEEL
aleksis_app_untis-3.0.dist-info/entry_points.txt
aleksis_app_untis-3.0.dist-info/RECORD
