Metadata-Version: 2.1
Name: aleksis-app-untis
Version: 3.0
Summary: AlekSIS (School Information System) — App for Untis import
Home-page: https://aleksis.org/
License: EUPL-1.2-or-later
Keywords: SIS,education,school,timetable,plans
Author: Dominik George
Author-email: dominik.george@teckids.org
Maintainer: Jonathan Weth
Maintainer-email: dev@jonathanweth.de
Requires-Python: >=3.9,<4.0
Classifier: Development Status :: 5 - Production/Stable
Classifier: Environment :: Web Environment
Classifier: Framework :: Django :: 3.0
Classifier: Intended Audience :: Education
Classifier: License :: Other/Proprietary License
Classifier: Programming Language :: Python :: 3
Classifier: Programming Language :: Python :: 3.9
Classifier: Programming Language :: Python :: 3.10
Classifier: Programming Language :: Python :: 3.11
Classifier: Topic :: Education
Classifier: Typing :: Typed
Requires-Dist: aleksis-app-chronos (>=3.0,<4.0)
Requires-Dist: aleksis-core (>=3.0,<4.0)
Requires-Dist: defusedxml (>=0.7.0,<0.8.0)
Requires-Dist: mysqlclient (>=2.0.0,<3.0.0)
Requires-Dist: tqdm (>=4.44.1,<5.0.0)
Project-URL: Documentation, https://aleksis.org/AlekSIS/docs/html/
Project-URL: Repository, https://edugit.org/AlekSIS/official/AlekSIS-App-Untis
